{"type": "FeatureCollection", "features": [{"type": "Feature", "geometry": {"type": "Point", "coordinates": [14.41561, 35.95064]}, "properties": {"source_label": "bahar", "sentence_idx": 1609}}, {"type": "Feature", "geometry": {"type": "Point", "coordinates": [14.41561, 35.95064]}, "properties": {"source_label": "bahar", "sentence_idx": 1616}}, {"type": "Feature", "geometry": {"type": "Point", "coordinates": [7.23142, 53.0252]}, "properties": {"source_label": "rheede", "sentence_idx": 1619}}]}