{"type": "FeatureCollection", "features": [{"type": "Feature", "geometry": {"type": "Point", "coordinates": [59.0, 35.0]}, "properties": {"source_label": "khorafan", "sentence_idx": 1381}}, {"type": "Feature", "geometry": {"type": "Point", "coordinates": [52.53113, 29.61031]}, "properties": {"source_label": "schiras", "sentence_idx": 1383}}, {"type": "Feature", "geometry": {"type": "Point", "coordinates": [52.53113, 29.61031]}, "properties": {"source_label": "schiras", "sentence_idx": 1386}}, {"type": "Feature", "geometry": {"type": "Point", "coordinates": [52.53113, 29.61031]}, "properties": {"source_label": "schiras", "sentence_idx": 1394}}, {"type": "Feature", "geometry": {"type": "Point", "coordinates": [52.53113, 29.61031]}, "properties": {"source_label": "schiras", "sentence_idx": 1396}}]}