{"type": "FeatureCollection", "features": [{"type": "Feature", "geometry": {"type": "Point", "coordinates": [53.0, 32.0]}, "properties": {"source_label": "persien", "sentence_idx": 839}}, {"type": "Feature", "geometry": {"type": "Point", "coordinates": [51.28333, 33.88333]}, "properties": {"source_label": "Kaschan", "sentence_idx": 839}}, {"type": "Feature", "geometry": {"type": "Point", "coordinates": [53.0, 32.0]}, "properties": {"source_label": "persien", "sentence_idx": 844}}, {"type": "Feature", "geometry": {"type": "Point", "coordinates": [52.53113, 29.61031]}, "properties": {"source_label": "schiras", "sentence_idx": 848}}, {"type": "Feature", "geometry": {"type": "Point", "coordinates": [53.0, 32.0]}, "properties": {"source_label": "persien", "sentence_idx": 857}}, {"type": "Feature", "geometry": {"type": "Point", "coordinates": [53.0, 32.0]}, "properties": {"source_label": "persien", "sentence_idx": 864}}, {"type": "Feature", "geometry": {"type": "Point", "coordinates": [53.0, 32.0]}, "properties": {"source_label": "persien", "sentence_idx": 867}}, {"type": "Feature", "geometry": {"type": "Point", "coordinates": [53.0, 32.0]}, "properties": {"source_label": "persien", "sentence_idx": 870}}]}