{"type": "FeatureCollection", "features": [{"type": "Feature", "geometry": {"type": "Point", "coordinates": [53.0, 29.0]}, "properties": {"source_label": "Farsistan", "sentence_idx": 1049}}, {"type": "Feature", "geometry": {"type": "Point", "coordinates": [52.53113, 29.61031]}, "properties": {"source_label": "schiras", "sentence_idx": 1049}}, {"type": "Feature", "geometry": {"type": "Point", "coordinates": [52.89, 29.9368]}, "properties": {"source_label": "persepolis", "sentence_idx": 1051}}, {"type": "Feature", "geometry": {"type": "Point", "coordinates": [52.53113, 29.61031]}, "properties": {"source_label": "schiras", "sentence_idx": 1058}}, {"type": "Feature", "geometry": {"type": "Point", "coordinates": [52.89, 29.9368]}, "properties": {"source_label": "persepolis", "sentence_idx": 1058}}]}