{"type": "FeatureCollection", "features": [{"type": "Feature", "geometry": {"type": "Point", "coordinates": [52.53113, 29.61031]}, "properties": {"source_label": "schiras", "sentence_idx": 1446}}, {"type": "Feature", "geometry": {"type": "Point", "coordinates": [51.67462, 32.65246]}, "properties": {"source_label": "ispahan", "sentence_idx": 1450}}, {"type": "Feature", "geometry": {"type": "Point", "coordinates": [51.67462, 32.65246]}, "properties": {"source_label": "ispahan", "sentence_idx": 1453}}, {"type": "Feature", "geometry": {"type": "Point", "coordinates": [53.0, 29.0]}, "properties": {"source_label": "Farsistan", "sentence_idx": 1455}}, {"type": "Feature", "geometry": {"type": "Point", "coordinates": [51.67462, 32.65246]}, "properties": {"source_label": "ispahan", "sentence_idx": 1456}}, {"type": "Feature", "geometry": {"type": "Point", "coordinates": [52.53113, 29.61031]}, "properties": {"source_label": "schiras", "sentence_idx": 1458}}, {"type": "Feature", "geometry": {"type": "Point", "coordinates": [51.67462, 32.65246]}, "properties": {"source_label": "ispahan", "sentence_idx": 1459}}]}