{"type": "FeatureCollection", "features": [{"type": "Feature", "geometry": {"type": "Point", "coordinates": [86.35916, 25.40195]}, "properties": {"source_label": "Sanha", "sentence_idx": 1832}}, {"type": "Feature", "geometry": {"type": "Point", "coordinates": [86.35916, 25.40195]}, "properties": {"source_label": "Sanha", "sentence_idx": 1837}}, {"type": "Feature", "geometry": {"type": "Point", "coordinates": [90.5, 27.5]}, "properties": {"source_label": "butan", "sentence_idx": 1838}}]}