{"type": "FeatureCollection", "features": [{"type": "Feature", "geometry": {"type": "Point", "coordinates": [18.04436, 48.89452]}, "properties": {"source_label": "trentschin", "sentence_idx": 1509}}, {"type": "Feature", "geometry": {"type": "Point", "coordinates": [20.0, 47.0]}, "properties": {"source_label": "ungarn", "sentence_idx": 1512}}, {"type": "Feature", "geometry": {"type": "Point", "coordinates": [16.37208, 48.20849]}, "properties": {"source_label": "wien", "sentence_idx": 1512}}]}