{"type": "FeatureCollection", "features": [{"type": "Feature", "geometry": {"type": "Point", "coordinates": [14.26811, 40.85216]}, "properties": {"source_label": "neapel", "sentence_idx": 326}}, {"type": "Feature", "geometry": {"type": "Point", "coordinates": [14.26811, 40.85216]}, "properties": {"source_label": "neapel", "sentence_idx": 341}}, {"type": "Feature", "geometry": {"type": "Point", "coordinates": [14.26811, 40.85216]}, "properties": {"source_label": "neapel", "sentence_idx": 345}}]}