{"type": "FeatureCollection", "features": [{"type": "Feature", "geometry": {"type": "Point", "coordinates": [10.92539, 44.64783]}, "properties": {"source_label": "modena", "sentence_idx": 2084}}, {"type": "Feature", "geometry": {"type": "Point", "coordinates": [11.50835, 52.49718]}, "properties": {"source_label": "stahrenberg", "sentence_idx": 2090}}, {"type": "Feature", "geometry": {"type": "Point", "coordinates": [16.37208, 48.20849]}, "properties": {"source_label": "wien", "sentence_idx": 2101}}, {"type": "Feature", "geometry": {"type": "Point", "coordinates": [16.59049, 47.68501]}, "properties": {"source_label": "oedenburg", "sentence_idx": 2103}}]}