{"type": "FeatureCollection", "features": [{"type": "Feature", "geometry": {"type": "Point", "coordinates": [17.10674, 48.14816]}, "properties": {"source_label": "pre\u00dfburg", "sentence_idx": 658}}, {"type": "Feature", "geometry": {"type": "Point", "coordinates": [17.10674, 48.14816]}, "properties": {"source_label": "pre\u00dfburg", "sentence_idx": 659}}, {"type": "Feature", "geometry": {"type": "Point", "coordinates": [17.10674, 48.14816]}, "properties": {"source_label": "pre\u00dfburg", "sentence_idx": 660}}]}