{"type": "FeatureCollection", "features": [{"type": "Feature", "geometry": {"type": "Point", "coordinates": [13.06566, 52.39886]}, "properties": {"source_label": "potsdam", "sentence_idx": 618}}, {"type": "Feature", "geometry": {"type": "Point", "coordinates": [16.37208, 48.20849]}, "properties": {"source_label": "wien", "sentence_idx": 619}}, {"type": "Feature", "geometry": {"type": "Point", "coordinates": [29.66667, 45.33333]}, "properties": {"source_label": "donau", "sentence_idx": 622}}]}