{"type": "FeatureCollection", "features": [{"type": "Feature", "geometry": {"type": "Point", "coordinates": [73.36598, 33.71494]}, "properties": {"source_label": "mochha", "sentence_idx": 8305}}, {"type": "Feature", "geometry": {"type": "Point", "coordinates": [73.36598, 33.71494]}, "properties": {"source_label": "mochha", "sentence_idx": 8306}}, {"type": "Feature", "geometry": {"type": "Point", "coordinates": [73.36598, 33.71494]}, "properties": {"source_label": "mochha", "sentence_idx": 8308}}, {"type": "Feature", "geometry": {"type": "Point", "coordinates": [73.36598, 33.71494]}, "properties": {"source_label": "mochha", "sentence_idx": 8310}}, {"type": "Feature", "geometry": {"type": "Point", "coordinates": [73.36598, 33.71494]}, "properties": {"source_label": "mochha", "sentence_idx": 8315}}, {"type": "Feature", "geometry": {"type": "Point", "coordinates": [73.36598, 33.71494]}, "properties": {"source_label": "mochha", "sentence_idx": 8316}}, {"type": "Feature", "geometry": {"type": "Point", "coordinates": [73.36598, 33.71494]}, "properties": {"source_label": "mochha", "sentence_idx": 8317}}, {"type": "Feature", "geometry": {"type": "Point", "coordinates": [73.36598, 33.71494]}, "properties": {"source_label": "mochha", "sentence_idx": 8322}}, {"type": "Feature", "geometry": {"type": "Point", "coordinates": [73.36598, 33.71494]}, "properties": {"source_label": "mochha", "sentence_idx": 8327}}, {"type": "Feature", "geometry": {"type": "Point", "coordinates": [73.36598, 33.71494]}, "properties": {"source_label": "mochha", "sentence_idx": 8338}}]}