{"type": "FeatureCollection", "features": [{"type": "Feature", "geometry": {"type": "Point", "coordinates": [73.36598, 33.71494]}, "properties": {"source_label": "mochha", "sentence_idx": 9602}}, {"type": "Feature", "geometry": {"type": "Point", "coordinates": [73.36598, 33.71494]}, "properties": {"source_label": "mochha", "sentence_idx": 9605}}, {"type": "Feature", "geometry": {"type": "Point", "coordinates": [73.36598, 33.71494]}, "properties": {"source_label": "mochha", "sentence_idx": 9610}}]}