{"type": "FeatureCollection", "features": [{"type": "Feature", "geometry": {"type": "Point", "coordinates": [42.69093, 15.70309]}, "properties": {"source_label": "loheia", "sentence_idx": 6145}}, {"type": "Feature", "geometry": {"type": "Point", "coordinates": [42.69093, 15.70309]}, "properties": {"source_label": "loheia", "sentence_idx": 6157}}, {"type": "Feature", "geometry": {"type": "Point", "coordinates": [42.69093, 15.70309]}, "properties": {"source_label": "loheia", "sentence_idx": 6162}}]}