{"type": "FeatureCollection", "features": [{"type": "Feature", "geometry": {"type": "Point", "coordinates": [39.18624, 21.49012]}, "properties": {"source_label": "dschidda", "sentence_idx": 5763}}, {"type": "Feature", "geometry": {"type": "Point", "coordinates": [42.69093, 15.70309]}, "properties": {"source_label": "loheia", "sentence_idx": 5763}}, {"type": "Feature", "geometry": {"type": "Point", "coordinates": [45.0, 25.0]}, "properties": {"source_label": "arabien", "sentence_idx": 5766}}]}