{"type": "FeatureCollection", "features": [{"type": "Feature", "geometry": {"type": "Point", "coordinates": [39.18624, 21.49012]}, "properties": {"source_label": "dschidda", "sentence_idx": 5981}}, {"type": "Feature", "geometry": {"type": "Point", "coordinates": [42.69093, 15.70309]}, "properties": {"source_label": "loheia", "sentence_idx": 5982}}, {"type": "Feature", "geometry": {"type": "Point", "coordinates": [42.69093, 15.70309]}, "properties": {"source_label": "loheia", "sentence_idx": 5989}}, {"type": "Feature", "geometry": {"type": "Point", "coordinates": [42.69093, 15.70309]}, "properties": {"source_label": "loheia", "sentence_idx": 5991}}, {"type": "Feature", "geometry": {"type": "Point", "coordinates": [42.95452, 14.79781]}, "properties": {"source_label": "hodeida", "sentence_idx": 5996}}, {"type": "Feature", "geometry": {"type": "Point", "coordinates": [39.18624, 21.49012]}, "properties": {"source_label": "dschidda", "sentence_idx": 5996}}, {"type": "Feature", "geometry": {"type": "Point", "coordinates": [39.18624, 21.49012]}, "properties": {"source_label": "dschidda", "sentence_idx": 5997}}, {"type": "Feature", "geometry": {"type": "Point", "coordinates": [42.69093, 15.70309]}, "properties": {"source_label": "loheia", "sentence_idx": 5997}}, {"type": "Feature", "geometry": {"type": "Point", "coordinates": [42.69093, 15.70309]}, "properties": {"source_label": "loheia", "sentence_idx": 6003}}, {"type": "Feature", "geometry": {"type": "Point", "coordinates": [42.69093, 15.70309]}, "properties": {"source_label": "loheia", "sentence_idx": 6008}}, {"type": "Feature", "geometry": {"type": "Point", "coordinates": [39.18624, 21.49012]}, "properties": {"source_label": "dschidda", "sentence_idx": 6014}}, {"type": "Feature", "geometry": {"type": "Point", "coordinates": [42.69093, 15.70309]}, "properties": {"source_label": "loheia", "sentence_idx": 6014}}, {"type": "Feature", "geometry": {"type": "Point", "coordinates": [42.69093, 15.70309]}, "properties": {"source_label": "loheia", "sentence_idx": 6017}}, {"type": "Feature", "geometry": {"type": "Point", "coordinates": [42.95452, 14.79781]}, "properties": {"source_label": "hodeida", "sentence_idx": 6018}}, {"type": "Feature", "geometry": {"type": "Point", "coordinates": [45.0, 25.0]}, "properties": {"source_label": "arabien", "sentence_idx": 6020}}, {"type": "Feature", "geometry": {"type": "Point", "coordinates": [45.0, 25.0]}, "properties": {"source_label": "arabien", "sentence_idx": 6026}}, {"type": "Feature", "geometry": {"type": "Point", "coordinates": [39.18624, 21.49012]}, "properties": {"source_label": "dschidda", "sentence_idx": 6034}}, {"type": "Feature", "geometry": {"type": "Point", "coordinates": [42.69093, 15.70309]}, "properties": {"source_label": "loheia", "sentence_idx": 6034}}]}