{"type": "FeatureCollection", "features": [{"type": "Feature", "geometry": {"type": "Point", "coordinates": [14.739, 13.444]}, "properties": {"source_label": "berim", "sentence_idx": 2198}}, {"type": "Feature", "geometry": {"type": "Point", "coordinates": [5.38333, 5.36667]}, "properties": {"source_label": "pocock", "sentence_idx": 2203}}, {"type": "Feature", "geometry": {"type": "Point", "coordinates": [5.38333, 5.36667]}, "properties": {"source_label": "pocock", "sentence_idx": 2213}}, {"type": "Feature", "geometry": {"type": "Point", "coordinates": [6.0, 5.5]}, "properties": {"source_label": "delta", "sentence_idx": 2215}}]}