{"type": "FeatureCollection", "features": [{"type": "Feature", "geometry": {"type": "Point", "coordinates": [79.0, 22.0]}, "properties": {"source_label": "indien", "sentence_idx": 8294}}, {"type": "Feature", "geometry": {"type": "Point", "coordinates": [79.0, 22.0]}, "properties": {"source_label": "indien", "sentence_idx": 8303}}, {"type": "Feature", "geometry": {"type": "Point", "coordinates": [72.88261, 19.07283]}, "properties": {"source_label": "bombay", "sentence_idx": 8311}}]}