{"type": "FeatureCollection", "features": [{"type": "Feature", "geometry": {"type": "Point", "coordinates": [29.91582, 31.20176]}, "properties": {"source_label": "alexandrien", "sentence_idx": 1157}}, {"type": "Feature", "geometry": {"type": "Point", "coordinates": [29.91582, 31.20176]}, "properties": {"source_label": "alexandrien", "sentence_idx": 1166}}, {"type": "Feature", "geometry": {"type": "Point", "coordinates": [29.91582, 31.20176]}, "properties": {"source_label": "alexandrien", "sentence_idx": 1167}}, {"type": "Feature", "geometry": {"type": "Point", "coordinates": [30.0, 27.0]}, "properties": {"source_label": "egypten", "sentence_idx": 1168}}, {"type": "Feature", "geometry": {"type": "Point", "coordinates": [29.91582, 31.20176]}, "properties": {"source_label": "alexandrien", "sentence_idx": 1172}}, {"type": "Feature", "geometry": {"type": "Point", "coordinates": [30.0, 27.0]}, "properties": {"source_label": "egypten", "sentence_idx": 1172}}, {"type": "Feature", "geometry": {"type": "Point", "coordinates": [29.91582, 31.20176]}, "properties": {"source_label": "alexandrien", "sentence_idx": 1176}}, {"type": "Feature", "geometry": {"type": "Point", "coordinates": [29.91582, 31.20176]}, "properties": {"source_label": "alexandrien", "sentence_idx": 1178}}, {"type": "Feature", "geometry": {"type": "Point", "coordinates": [29.91582, 31.20176]}, "properties": {"source_label": "alexandrien", "sentence_idx": 1179}}, {"type": "Feature", "geometry": {"type": "Point", "coordinates": [28.94966, 41.01384]}, "properties": {"source_label": "constantinopel", "sentence_idx": 1179}}, {"type": "Feature", "geometry": {"type": "Point", "coordinates": [30.0, 27.0]}, "properties": {"source_label": "egypten", "sentence_idx": 1180}}, {"type": "Feature", "geometry": {"type": "Point", "coordinates": [29.91582, 31.20176]}, "properties": {"source_label": "alexandrien", "sentence_idx": 1181}}, {"type": "Feature", "geometry": {"type": "Point", "coordinates": [29.91582, 31.20176]}, "properties": {"source_label": "alexandrien", "sentence_idx": 1186}}, {"type": "Feature", "geometry": {"type": "Point", "coordinates": [29.91582, 31.20176]}, "properties": {"source_label": "alexandrien", "sentence_idx": 1188}}]}