{"type": "FeatureCollection", "features": [{"type": "Feature", "geometry": {"type": "Point", "coordinates": [19.985, 41.9125]}, "properties": {"source_label": "rras", "sentence_idx": 7520}}, {"type": "Feature", "geometry": {"type": "Point", "coordinates": [9.14062, 48.69096]}, "properties": {"source_label": "europa", "sentence_idx": 7521}}, {"type": "Feature", "geometry": {"type": "Point", "coordinates": [19.985, 41.9125]}, "properties": {"source_label": "rras", "sentence_idx": 7526}}, {"type": "Feature", "geometry": {"type": "Point", "coordinates": [9.14062, 48.69096]}, "properties": {"source_label": "europa", "sentence_idx": 7534}}, {"type": "Feature", "geometry": {"type": "Point", "coordinates": [19.985, 41.9125]}, "properties": {"source_label": "rras", "sentence_idx": 7538}}]}