{"type": "FeatureCollection", "features": [{"type": "Feature", "geometry": {"type": "Point", "coordinates": [39.18624, 21.49012]}, "properties": {"source_label": "dschidda", "sentence_idx": 8370}}, {"type": "Feature", "geometry": {"type": "Point", "coordinates": [45.0, 25.0]}, "properties": {"source_label": "arabien", "sentence_idx": 8377}}, {"type": "Feature", "geometry": {"type": "Point", "coordinates": [39.18624, 21.49012]}, "properties": {"source_label": "dschidda", "sentence_idx": 8391}}, {"type": "Feature", "geometry": {"type": "Point", "coordinates": [39.18624, 21.49012]}, "properties": {"source_label": "dschidda", "sentence_idx": 8392}}, {"type": "Feature", "geometry": {"type": "Point", "coordinates": [39.18624, 21.49012]}, "properties": {"source_label": "dschidda", "sentence_idx": 8394}}, {"type": "Feature", "geometry": {"type": "Point", "coordinates": [39.18624, 21.49012]}, "properties": {"source_label": "dschidda", "sentence_idx": 8401}}, {"type": "Feature", "geometry": {"type": "Point", "coordinates": [39.18624, 21.49012]}, "properties": {"source_label": "dschidda", "sentence_idx": 8404}}, {"type": "Feature", "geometry": {"type": "Point", "coordinates": [42.95452, 14.79781]}, "properties": {"source_label": "hodeida", "sentence_idx": 8410}}, {"type": "Feature", "geometry": {"type": "Point", "coordinates": [45.0, 25.0]}, "properties": {"source_label": "arabien", "sentence_idx": 8419}}, {"type": "Feature", "geometry": {"type": "Point", "coordinates": [45.0, 25.0]}, "properties": {"source_label": "arabien", "sentence_idx": 8419}}, {"type": "Feature", "geometry": {"type": "Point", "coordinates": [39.18624, 21.49012]}, "properties": {"source_label": "dschidda", "sentence_idx": 8420}}]}