{"type": "FeatureCollection", "features": [{"type": "Feature", "geometry": {"type": "Point", "coordinates": [44.40088, 33.34058]}, "properties": {"source_label": "bagdad", "sentence_idx": 8534}}, {"type": "Feature", "geometry": {"type": "Point", "coordinates": [53.0, 32.0]}, "properties": {"source_label": "persien", "sentence_idx": 8543}}, {"type": "Feature", "geometry": {"type": "Point", "coordinates": [45.0, 25.0]}, "properties": {"source_label": "arabien", "sentence_idx": 8548}}]}