{"type": "FeatureCollection", "features": [{"type": "Feature", "geometry": {"type": "Point", "coordinates": [39.18624, 21.49012]}, "properties": {"source_label": "dschidda", "sentence_idx": 5340}}, {"type": "Feature", "geometry": {"type": "Point", "coordinates": [39.18624, 21.49012]}, "properties": {"source_label": "dschidda", "sentence_idx": 5355}}, {"type": "Feature", "geometry": {"type": "Point", "coordinates": [39.18624, 21.49012]}, "properties": {"source_label": "dschidda", "sentence_idx": 5357}}, {"type": "Feature", "geometry": {"type": "Point", "coordinates": [39.18624, 21.49012]}, "properties": {"source_label": "dschidda", "sentence_idx": 5358}}, {"type": "Feature", "geometry": {"type": "Point", "coordinates": [39.18624, 21.49012]}, "properties": {"source_label": "susbis dsjidda", "sentence_idx": 5374}}]}