{"type": "FeatureCollection", "features": [{"type": "Feature", "geometry": {"type": "Point", "coordinates": [31.81332, 31.41648]}, "properties": {"source_label": "damietta", "sentence_idx": 2716}}, {"type": "Feature", "geometry": {"type": "Point", "coordinates": [30.0, 27.0]}, "properties": {"source_label": "egypten", "sentence_idx": 2717}}, {"type": "Feature", "geometry": {"type": "Point", "coordinates": [32.0, 26.0]}, "properties": {"source_label": "oberegypten", "sentence_idx": 2722}}, {"type": "Feature", "geometry": {"type": "Point", "coordinates": [30.0, 27.0]}, "properties": {"source_label": "egypten", "sentence_idx": 2722}}, {"type": "Feature", "geometry": {"type": "Point", "coordinates": [30.0, 27.0]}, "properties": {"source_label": "egypten", "sentence_idx": 2723}}, {"type": "Feature", "geometry": {"type": "Point", "coordinates": [31.24967, 30.06263]}, "properties": {"source_label": "cairo", "sentence_idx": 2724}}, {"type": "Feature", "geometry": {"type": "Point", "coordinates": [30.0, 27.0]}, "properties": {"source_label": "egypten", "sentence_idx": 2724}}, {"type": "Feature", "geometry": {"type": "Point", "coordinates": [32.0, 26.0]}, "properties": {"source_label": "oberegypten", "sentence_idx": 2725}}, {"type": "Feature", "geometry": {"type": "Point", "coordinates": [31.24967, 30.06263]}, "properties": {"source_label": "masr el atik", "sentence_idx": 2729}}, {"type": "Feature", "geometry": {"type": "Point", "coordinates": [30.0, 27.0]}, "properties": {"source_label": "egypten", "sentence_idx": 2729}}]}