{"type": "FeatureCollection", "features": [{"type": "Feature", "geometry": {"type": "Point", "coordinates": [29.91582, 31.20176]}, "properties": {"source_label": "alexandrien", "sentence_idx": 988}}, {"type": "Feature", "geometry": {"type": "Point", "coordinates": [29.91582, 31.20176]}, "properties": {"source_label": "alexandrien", "sentence_idx": 996}}, {"type": "Feature", "geometry": {"type": "Point", "coordinates": [29.91582, 31.20176]}, "properties": {"source_label": "alexandrien", "sentence_idx": 997}}, {"type": "Feature", "geometry": {"type": "Point", "coordinates": [29.91582, 31.20176]}, "properties": {"source_label": "alexandrien", "sentence_idx": 1008}}, {"type": "Feature", "geometry": {"type": "Point", "coordinates": [29.91582, 31.20176]}, "properties": {"source_label": "alexandrien", "sentence_idx": 1010}}, {"type": "Feature", "geometry": {"type": "Point", "coordinates": [29.91582, 31.20176]}, "properties": {"source_label": "alexandrien", "sentence_idx": 1013}}, {"type": "Feature", "geometry": {"type": "Point", "coordinates": [29.91582, 31.20176]}, "properties": {"source_label": "alexandrien", "sentence_idx": 1017}}, {"type": "Feature", "geometry": {"type": "Point", "coordinates": [29.91582, 31.20176]}, "properties": {"source_label": "alexandrien", "sentence_idx": 1019}}, {"type": "Feature", "geometry": {"type": "Point", "coordinates": [29.91582, 31.20176]}, "properties": {"source_label": "alexandrien", "sentence_idx": 1023}}, {"type": "Feature", "geometry": {"type": "Point", "coordinates": [29.91582, 31.20176]}, "properties": {"source_label": "alexandrien", "sentence_idx": 1029}}, {"type": "Feature", "geometry": {"type": "Point", "coordinates": [29.91582, 31.20176]}, "properties": {"source_label": "alexandrien", "sentence_idx": 1037}}, {"type": "Feature", "geometry": {"type": "Point", "coordinates": [29.91582, 31.20176]}, "properties": {"source_label": "alexandrien", "sentence_idx": 1042}}, {"type": "Feature", "geometry": {"type": "Point", "coordinates": [29.91582, 31.20176]}, "properties": {"source_label": "alexandrien", "sentence_idx": 1048}}]}