{"type": "FeatureCollection", "features": [{"type": "Feature", "geometry": {"type": "Point", "coordinates": [39.18624, 21.49012]}, "properties": {"source_label": "dschidda", "sentence_idx": 5532}}, {"type": "Feature", "geometry": {"type": "Point", "coordinates": [39.18624, 21.49012]}, "properties": {"source_label": "dschidda", "sentence_idx": 5534}}, {"type": "Feature", "geometry": {"type": "Point", "coordinates": [39.18624, 21.49012]}, "properties": {"source_label": "dschidda", "sentence_idx": 5537}}, {"type": "Feature", "geometry": {"type": "Point", "coordinates": [39.18624, 21.49012]}, "properties": {"source_label": "dschidda", "sentence_idx": 5541}}, {"type": "Feature", "geometry": {"type": "Point", "coordinates": [39.18624, 21.49012]}, "properties": {"source_label": "dschidda", "sentence_idx": 5543}}, {"type": "Feature", "geometry": {"type": "Point", "coordinates": [39.18624, 21.49012]}, "properties": {"source_label": "dschidda", "sentence_idx": 5545}}, {"type": "Feature", "geometry": {"type": "Point", "coordinates": [39.18624, 21.49012]}, "properties": {"source_label": "dschidda", "sentence_idx": 5553}}, {"type": "Feature", "geometry": {"type": "Point", "coordinates": [39.18624, 21.49012]}, "properties": {"source_label": "dschidda", "sentence_idx": 5555}}, {"type": "Feature", "geometry": {"type": "Point", "coordinates": [39.18624, 21.49012]}, "properties": {"source_label": "dschidda", "sentence_idx": 5557}}, {"type": "Feature", "geometry": {"type": "Point", "coordinates": [39.18624, 21.49012]}, "properties": {"source_label": "dschidda", "sentence_idx": 5562}}, {"type": "Feature", "geometry": {"type": "Point", "coordinates": [39.18624, 21.49012]}, "properties": {"source_label": "dschidda", "sentence_idx": 5565}}, {"type": "Feature", "geometry": {"type": "Point", "coordinates": [45.0, 25.0]}, "properties": {"source_label": "arabien", "sentence_idx": 5566}}]}