{"type": "FeatureCollection", "features": [{"type": "Feature", "geometry": {"type": "Point", "coordinates": [9.0, 40.0]}, "properties": {"source_label": "sardinien", "sentence_idx": 8521}}, {"type": "Feature", "geometry": {"type": "Point", "coordinates": [9.14062, 48.69096]}, "properties": {"source_label": "europa", "sentence_idx": 8521}}, {"type": "Feature", "geometry": {"type": "Point", "coordinates": [7.68682, 45.07049]}, "properties": {"source_label": "turin", "sentence_idx": 8522}}, {"type": "Feature", "geometry": {"type": "Point", "coordinates": [12.83333, 42.83333]}, "properties": {"source_label": "italien", "sentence_idx": 8537}}, {"type": "Feature", "geometry": {"type": "Point", "coordinates": [12.83333, 42.83333]}, "properties": {"source_label": "italien", "sentence_idx": 8541}}, {"type": "Feature", "geometry": {"type": "Point", "coordinates": [9.0, 48.0]}, "properties": {"source_label": "schwaben", "sentence_idx": 8543}}, {"type": "Feature", "geometry": {"type": "Point", "coordinates": [7.68682, 45.07049]}, "properties": {"source_label": "turin", "sentence_idx": 8543}}, {"type": "Feature", "geometry": {"type": "Point", "coordinates": [12.83333, 42.83333]}, "properties": {"source_label": "italien", "sentence_idx": 8543}}, {"type": "Feature", "geometry": {"type": "Point", "coordinates": [9.0, 40.0]}, "properties": {"source_label": "sardinien", "sentence_idx": 8545}}, {"type": "Feature", "geometry": {"type": "Point", "coordinates": [10.0, 56.0]}, "properties": {"source_label": "daenemark", "sentence_idx": 8548}}, {"type": "Feature", "geometry": {"type": "Point", "coordinates": [9.14062, 48.69096]}, "properties": {"source_label": "europa", "sentence_idx": 8550}}, {"type": "Feature", "geometry": {"type": "Point", "coordinates": [2.0, 46.0]}, "properties": {"source_label": "frankreich", "sentence_idx": 8553}}, {"type": "Feature", "geometry": {"type": "Point", "coordinates": [9.14062, 48.69096]}, "properties": {"source_label": "europa", "sentence_idx": 8553}}, {"type": "Feature", "geometry": {"type": "Point", "coordinates": [2.3488, 48.85341]}, "properties": {"source_label": "paris", "sentence_idx": 8555}}, {"type": "Feature", "geometry": {"type": "Point", "coordinates": [2.0, 46.0]}, "properties": {"source_label": "frankreich", "sentence_idx": 8556}}]}