{"type": "FeatureCollection", "features": [{"type": "Feature", "geometry": {"type": "Point", "coordinates": [42.69093, 15.70309]}, "properties": {"source_label": "loheia", "sentence_idx": 6113}}, {"type": "Feature", "geometry": {"type": "Point", "coordinates": [45.0, 25.0]}, "properties": {"source_label": "arabien", "sentence_idx": 6117}}, {"type": "Feature", "geometry": {"type": "Point", "coordinates": [42.69093, 15.70309]}, "properties": {"source_label": "loheia", "sentence_idx": 6118}}, {"type": "Feature", "geometry": {"type": "Point", "coordinates": [42.69093, 15.70309]}, "properties": {"source_label": "loheia", "sentence_idx": 6120}}, {"type": "Feature", "geometry": {"type": "Point", "coordinates": [42.69093, 15.70309]}, "properties": {"source_label": "loheia", "sentence_idx": 6128}}]}